.flake8
.gitignore
CHANGES.rst
LICENSE
README.md
pyproject.toml
requirements.txt
setup.cfg
setup.py
.github/workflows/publish-to-pypi.yml
.github/workflows/python-package.yml
sregion/__init__.py
sregion/sregion.py
sregion/utils.py
sregion/version.py
sregion.egg-info/PKG-INFO
sregion.egg-info/SOURCES.txt
sregion.egg-info/dependency_links.txt
sregion.egg-info/requires.txt
sregion.egg-info/top_level.txt
sregion/tests/__init__.py
sregion/tests/test_sregion.py
sregion/tests/test_utils.py