Metadata-Version: 2.4
Name: sregion
Version: 1.5
Summary: Parsing of IVOA S_REGION strings
Home-page: http://github.com/gbrammer/sregion
Author: G. Brammer
Author-email: gbrammer@gmail.com
License: MIT
Project-URL: Source, https://github.com/gbrammer/sregion
Project-URL: Tracker, https://github.com/gbrammer/sregion/issues
Requires-Python: >=3.6
License-File: LICENSE
Requires-Dist: numpy
Requires-Dist: astropy
Requires-Dist: shapely>=2.0
Requires-Dist: scipy
Requires-Dist: matplotlib
Provides-Extra: test
Requires-Dist: pytest>=5.1; extra == "test"
Requires-Dist: flake8; extra == "test"
Dynamic: license-file
